ageqrp/__init__.py
ageqrp/query_result_parser.py
ageqrp-0.2.0.dist-info/METADATA
ageqrp-0.2.0.dist-info/WHEEL
ageqrp-0.2.0.dist-info/licenses/LICENSE
ageqrp-0.2.0.dist-info/RECORD
