Metadata-Version: 2.3
Name: ageqrp
Version: 0.2.0
Summary: Query Results Parser (QRP) for Apache AGE database queries using psycopg
Project-URL: Homepage, https://github.com/cjoakim/ageqrp
Project-URL: Issues, https://github.com/cjoakim/ageqrp/issues
Project-URL: Repository, https://github.com/cjoakim/ageqrp
Author-email: Chris Joakim <christopher.joakim@gmail.com>
Maintainer-email: Chris Joakim <christopher.joakim@gmail.com>
License: MIT License
Keywords: Apache AGE,parser,psycopg,query,results
Classifier: License :: OSI Approved :: MIT License
Classifier: Operating System :: OS Independent
Classifier: Programming Language :: Python :: 3
Requires-Python: >=3.11
